trytond/modules/health_inpatient_calendar/COPYING
trytond/modules/health_inpatient_calendar/README.rst
trytond/modules/health_inpatient_calendar/__init__.py
trytond/modules/health_inpatient_calendar/health_inpatient_calendar.py
trytond/modules/health_inpatient_calendar/health_inpatient_calendar_view.xml
trytond/modules/health_inpatient_calendar/locale/ar.po
trytond/modules/health_inpatient_calendar/locale/de.po
trytond/modules/health_inpatient_calendar/locale/el.po
trytond/modules/health_inpatient_calendar/locale/eo.po
trytond/modules/health_inpatient_calendar/locale/es.po
trytond/modules/health_inpatient_calendar/locale/fr.po
trytond/modules/health_inpatient_calendar/locale/health_inpatient_calendar.pot
trytond/modules/health_inpatient_calendar/locale/it_IT.po
trytond/modules/health_inpatient_calendar/locale/ja_JP.po
trytond/modules/health_inpatient_calendar/locale/ka.po
trytond/modules/health_inpatient_calendar/locale/lo.po
trytond/modules/health_inpatient_calendar/locale/pt_BR.po
trytond/modules/health_inpatient_calendar/locale/sv.po
trytond/modules/health_inpatient_calendar/locale/tr.po
trytond/modules/health_inpatient_calendar/locale/uk.po
trytond/modules/health_inpatient_calendar/locale/zh_CN.po
trytond/modules/health_inpatient_calendar/pyproject.toml
trytond/modules/health_inpatient_calendar/tests/__init__.py
trytond/modules/health_inpatient_calendar/tests/test_health_inpatient_calendar.py
trytond/modules/health_inpatient_calendar/tryton.cfg
trytond/modules/health_inpatient_calendar/view/gnuhealth_calendar_hospital_bed.xml
trytond/modules/health_inpatient_calendar/view/gnuhealth_calendar_inpatient_registration.xml
gnuhealth_inpatient_calendar-5.0.2.dist-info/METADATA
gnuhealth_inpatient_calendar-5.0.2.dist-info/WHEEL
gnuhealth_inpatient_calendar-5.0.2.dist-info/licenses/COPYING
gnuhealth_inpatient_calendar-5.0.2.dist-info/RECORD
